MANIFEST.in
Makefile
requirements.txt
setup.py
bin/themis
test/test_api.py
test/test_aws_pricing.py
test/test_emr_fetch_cluster_info.py
test/test_emr_scaling.py
test/test_kinesis_scaling.py
test/test_math_util.py
test/test_timeseries.py
themis/__init__.py
themis/api.py
themis/config.py
themis/constants.py
themis/server.py
themis/model/__init__.py
themis/model/aws_model.py
themis/model/emr_model.py
themis/model/kinesis_model.py
themis/model/resources_model.py
themis/monitoring/__init__.py
themis/monitoring/database.py
themis/monitoring/emr_monitoring.py
themis/monitoring/kinesis_monitoring.py
themis/monitoring/resources.py
themis/scaling/__init__.py
themis/scaling/emr_scaling.py
themis/scaling/kinesis_scaling.py
themis/util/__init__.py
themis/util/aws_common.py
themis/util/aws_pricing.py
themis/util/common.py
themis/util/exceptions.py
themis/util/expr.py
themis/util/math_util.py
themis/util/remote.py
themis/util/timeseries.py
themis/web/index.html
themis/web/package.json
themis/web/css/style.css
themis/web/css/lib/aui-experimental.css
themis/web/css/lib/aui-iconfonts.css
themis/web/css/lib/aui.css
themis/web/css/lib/fonts/atlassian-icons.ttf
themis/web/css/lib/fonts/atlassian-icons.woff
themis/web/img/favicon.png
themis/web/img/loading.gif
themis/web/img/scale_white.png
themis/web/img/scaling.png
themis/web/js/app.js
themis/web/js/lib/aui-experimental.js
themis/web/js/lib/aui.js
themis/web/views/config.html
themis/web/views/config.js
themis/web/views/emr.details.html
themis/web/views/emr.details.js
themis/web/views/emr.html
themis/web/views/emr.js
themis/web/views/emr.list.html
themis/web/views/emr.list.js
themis/web/views/kinesis.details.html
themis/web/views/kinesis.details.js
themis/web/views/kinesis.html
themis/web/views/kinesis.js
themis/web/views/kinesis.list.html
themis/web/views/kinesis.list.js
themis_autoscaler.egg-info/PKG-INFO
themis_autoscaler.egg-info/SOURCES.txt
themis_autoscaler.egg-info/dependency_links.txt
themis_autoscaler.egg-info/not-zip-safe
themis_autoscaler.egg-info/requires.txt
themis_autoscaler.egg-info/top_level.txt