Metadata-Version: 1.1
Name: themis-autoscaler
Version: 0.2.5
Summary: Themis is an autoscaler for Elastic Map Reduce (EMR) clusters on Amazon Web Services.
Home-page: http://github.com/atlassian/themis
Author: Waldemar Hummer
Author-email: waldemar.hummer@gmail.com
License: Apache License 2.0
Platform: UNKNOWN
Classifier: Programming Language :: Python :: 2
Classifier: Programming Language :: Python :: 2.6
Classifier: Programming Language :: Python :: 2.7
Classifier: Programming Language :: Python :: 3
Classifier: Programming Language :: Python :: 3.3
Classifier: License :: OSI Approved :: Apache Software License
Classifier: Topic :: Software Development :: Testing
